{
  "generated": "2026-07-16T22:24:37",
  "fear_greed": {
    "score": 38,
    "ma5": 25.4,
    "grade": "공포😨",
    "gauge": "🟦🟦🟦🟦⬜⬜⬜⬜⬜⬜",
    "date": "2026-07-16",
    "trend": 22
  },
  "holdings": [
    {
      "code": "047810",
      "name": "한국항공우주",
      "pct": 1.15
    },
    {
      "code": "189300",
      "name": "인텔리안테크",
      "pct": -6.26
    },
    {
      "code": "451760",
      "name": "컨텍",
      "pct": -0.64
    },
    {
      "code": "274090",
      "name": "켄코아에어로스페",
      "pct": -4.34
    },
    {
      "code": "209640",
      "name": "와이제이링크",
      "pct": -6.22
    },
    {
      "code": "474650",
      "name": "링크솔루션",
      "pct": -7.19
    }
  ],
  "signals": [],
  "grade_summary": [],
  "disclosures": []
}